pyloudnorm_custom_package/__init__.py
pyloudnorm_custom_package/iirfilter.py
pyloudnorm_custom_package/meter.py
pyloudnorm_custom_package/normalize.py
pyloudnorm_custom_package/util.py
pyloudnorm_custom_package-0.1.0.dist-info/LICENSE
pyloudnorm_custom_package-0.1.0.dist-info/METADATA
pyloudnorm_custom_package-0.1.0.dist-info/WHEEL
pyloudnorm_custom_package-0.1.0.dist-info/top_level.txt
pyloudnorm_custom_package-0.1.0.dist-info/RECORD
